{
  "meta": {
    "default_lang": "en",
    "available_langs": ["en", "id"]
  },
  "strings": {
    "already_registered": {
      "en": "You are already registered, no further action is required.",
      "id": "Kamu udah terdaftar, nggak ada tindakan lebih lanjut yang diperluin."
    },
    "registration_complete": {
      "en": "**Registration Complete**\n-# You received a small bonus to get started:",
      "id": "**Pendaftaran Berhasil**\n-# Kamu dapet bonus kecil untuk memulai:"
    },
    "access_denied": {
      "en": "**Access Denied**\n-# Your account has been flagged for potential bot activity. If you believe this is a mistake, please contact <@782922849169178657>",
      "id": "**Akses Ditolak**\n-# Akunmu ditandai karena terindikasi aktivitas bot. Jika kamu yakin ini keliru, bisa hubungi <@782922849169178657>"
    },
    "not_registered": {
      "en": "You are not registered, type `register` to continue.",
      "id": "Kamu belum terdaftar, ketik `register` untuk mendaftar."
    },
    "invalid_interaction": {
      "en": "This interaction is not for you.",
      "id": "Interaksi ini bukan buat kamu."
    },
    "booster": {
      "en": "**Booster Exclusive**\n-# Boost this server to unlock this command and other exclusive benefits!",
      "id": "**Eksklusif Booster**\n-# Boost server ini untuk membuka command ini dan dapetin benefit eksklusif lainnya!"
    },
    "cooldown": {
      "en": "You are on cooldown, retry <t:$sum[$getTimestamp;$getCooldown[global]]:R>.",
      "id": "Kamu lagi kena cooldown, coba lagi <t:$sum[$getTimestamp;$getCooldown[global]]:R>."
    },
    "cooldown_leaderboard": {
      "en": "Leaderboard updated recently, retry later.",
      "id": "Papan peringkat baru aja di-update, coba lagi nanti."
    },
    "cooldown_daily": {
      "en": "You have already claimed your daily, come back <t:$var[timestampCd]:R> for the next one.",
      "id": "Kamu udah klaim hadiah harian, kembali lagi <t:$var[timestampCd]:R> buat klaim berikutnya."
    },
    "cooldown_hourly": {
      "en": "You have already claimed your hourly, come back <t:$sum[$getTimestamp;$getCooldown[global]]:R> for the next one.",
      "id": "Kamu udah klaim hadiah per jam, kembali lagi <t:$sum[$getTimestamp;$getCooldown[global]]:R> buat klaim berikutnya."
    },
    "cooldown_weekly": {
      "en": "You have already claimed your weekly, come back <t:$sum[$getTimestamp;$getCooldown[global]]:R> for the next one.",
      "id": "Kamu udah klaim hadiah mingguan, kembali lagi <t:$sum[$getTimestamp;$getCooldown[global]]:R> buat klaim berikutnya."
    },
    "daily": {
      "en": "**Daily Reward**\n-# $if[$var[streak]>1]You are on a **$numberSeparator[$var[streak];$json[sep]]**-day streak! You $elseYou checked in and $endifreceived:",
      "id": "**Hadiah Harian**\n-# $if[$var[streak]>1]**$numberSeparator[$var[streak];$json[sep]]** hari berturut-turut! Kamu $elseKamu check-in dan $endifdapet:"
    },
    "hourly": {
      "en": "**Hourly Reward**\n-# You checked in and received:",
      "id": "**Hadiah Per Jam**\n-# Kamu check-in dan dapet:"
    },
    "weekly": {
      "en": "**Weekly Reward**\n-# You checked in and received:",
      "id": "**Hadiah Mingguan**\n-# Kamu check-in dan dapet:"
    },
    "streak_ended": {
      "en": "**Oops, Your Streak Ended**\n-# You missed your daily for **$numberSeparator[$var[forgot];$json[sep]]** days and lost your **$numberSeparator[$var[streak];$json[sep]]**-day streak",
      "id": "**Yah, Streak-mu Hangus**\n-# Kamu lupa check-in selama **$numberSeparator[$var[forgot];$json[sep]]** hari dan streak **$numberSeparator[$var[streak];$json[sep]]** hari kamu hilang"
    },
    "me_top": {
      "en": "You are in $var[#top] place",
      "id": "Kamu ada di peringkat ke-$replaceText[$replaceText[$replaceText[$replaceText[$var[#top];st;];nd;];rd;];th;]"
    },
    "me_point": {
      "en": "You need $numberSeparator[$var[pts-];$json[sep]] points to level up",
      "id": "Kamu butuh $numberSeparator[$var[pts-];$json[sep]] poin buat naik level"
    },
    "setting_updated": {
      "en": "Setting has been updated.",
      "id": "Setelan berhasil diperbarui."
    },
    "settings_language": {
      "en": "**Language**\n-# Select your preferred language",
      "id": "**Bahasa**\n-# Pilih bahasa yang kamu pakai"
    },
    "settings_separator": {
      "en": "**Number Separator**\n-# Select a symbol to separate thousands",
      "id": "**Pemisah Angka**\n-# Pilih simbol buat misahin angka ribuan"
    },
    "select_language": {
      "en": "Select a language",
      "id": "Pilih bahasa"
    },
    "select_separator": {
      "en": "Select a separator",
      "id": "Pilih pemisah"
    },
    "example": {
      "en": "Example:",
      "id": "Contoh:"
    },
    "comma": {
      "en": "Comma",
      "id": "Koma"
    },
    "period": {
      "en": "Period",
      "id": "Titik"
    },
    "none": {
      "en": "None",
      "id": "Tidak ada"
    }
  }
}
